{
  "employee_id": "d2510ee43c38ad6d",
  "employee_name": "Ballentine Motloung",
  "treatment_timeline": [
    {
      "date": "2023-09-18",
      "report_id": "25602ee7c0aa9100",
      "report_date": "2023-09-18",
      "doctor": "Alex Stuart",
      "nurse": "Sharonice Baaitjie",
      "employee_name": "Ballentine Motloung",
      "actions": [
        {
          "category": "Lifestyle",
          "recommendation": "Drink enough water",
          "status": "Ongoing",
          "source_field": "Special Investigation Notes"
        },
        {
          "category": "Lifestyle",
          "recommendation": "Not hold urine for long",
          "status": "Ongoing",
          "source_field": "Special Investigation Notes"
        },
        {
          "category": "Lifestyle",
          "recommendation": "Drink cranberry juice",
          "status": "Ongoing",
          "source_field": "Special Investigation Notes"
        }
      ]
    },
    {
      "date": "Not specified",
      "report_id": "1c4a6fd98d622dc8",
      "report_date": "Not specified",
      "doctor": "Alex Stuart",
      "nurse": "Ntombikayise Seane",
      "employee_name": "Ballentine Motloung",
      "actions": [
        {
          "category": "Screening",
          "recommendation": "pH 6, SG 1.015",
          "status": "Not specified",
          "source_field": "Special Investigation Notes"
        }
      ]
    }
  ],
  "generated_at": "2025-08-24 14:26:41",
  "total_reports": 2,
  "total_actions": 4,
  "medical_staff": {
    "doctors": [
      "Alex Stuart"
    ],
    "nurses": [
      "Ntombikayise Seane",
      "Sharonice Baaitjie"
    ]
  }
}