{
  "employee_id": "faigkijjw0zvxy7r",
  "employee_name": "Ancois Winsauer",
  "treatment_timeline": [
    {
      "date": "2023-08-23",
      "report_id": "97c589172d688059",
      "report_date": "Not specified",
      "doctor": "Melinda Whitfield",
      "nurse": "Lebo Cindi",
      "employee_name": "Ancois Winsauer",
      "actions": [
        {
          "category": "Supplements",
          "recommendation": "Ashwagandha and Theanine",
          "status": "Planned",
          "source_field": "VitaminsOrSupplements"
        },
        {
          "category": "Supplements",
          "recommendation": "Vit D (5000iu once daily)",
          "status": "Planned",
          "source_field": "VitaminsOrSupplements"
        },
        {
          "category": "Supplements",
          "recommendation": "Omega 3 (for cholesterol)",
          "status": "Planned",
          "source_field": "VitaminsOrSupplements"
        },
        {
          "category": "Supplements",
          "recommendation": "Magnesium (daily)",
          "status": "Planned",
          "source_field": "VitaminsOrSupplements"
        },
        {
          "category": "Women's Health",
          "recommendation": "Visit a general practitioner or a gynaecologists for a Pap smear",
          "status": "Planned",
          "source_field": "WomensHealthRecommendation"
        }
      ]
    }
  ],
  "generated_at": "2025-08-24 14:52:57",
  "total_reports": 1,
  "total_actions": 5,
  "medical_staff": {
    "doctors": [
      "Melinda Whitfield"
    ],
    "nurses": [
      "Lebo Cindi"
    ]
  }
}