{
  "employee_id": "kylpc9p96ox5nzcy",
  "employee_name": "Nanagolo Phiri",
  "treatment_timeline": [
    {
      "date": "Not specified",
      "report_id": "7d5ec43990b980e2",
      "report_date": "Not specified",
      "doctor": "Not specified",
      "nurse": "Lebo Cindi",
      "employee_name": "Nanagolo Phiri",
      "actions": [
        {
          "category": "Women's Health",
          "recommendation": "Visit a general practitioner or a gynaecologist for a Pap smear and a Radiologist for a mammogram every 1-2years",
          "status": "Planned",
          "source_field": "Women's Health Recommendations"
        },
        {
          "category": "Lifestyle",
          "recommendation": "Reduce alcohol to improve raised liver enzymes",
          "status": "Planned",
          "source_field": "LabTestRecommendation"
        },
        {
          "category": "Lifestyle",
          "recommendation": "Adjust lifestyle as advised and review in 6 months for abnormal cholesterol, fasting insulin and inflammation levels",
          "status": "Planned",
          "source_field": "LabTestRecommendation"
        },
        {
          "category": "Supplements",
          "recommendation": "Supplement for at least 3 months for low Vitamin D levels",
          "status": "Planned",
          "source_field": "LabTestRecommendation"
        },
        {
          "category": "Lifestyle",
          "recommendation": "Choose a healthy lifestyle to reduce your risk for developing familial related illnesses",
          "status": "Ongoing",
          "source_field": "MedicalHistoryRecommendation"
        }
      ]
    }
  ],
  "generated_at": "2025-08-24 15:22:08",
  "total_reports": 1,
  "total_actions": 5,
  "medical_staff": {
    "doctors": [],
    "nurses": [
      "Lebo Cindi"
    ]
  }
}