{
  "employee_id": "8c4f8ba9c09fa530",
  "employee_name": "Lesego Mkhehlane",
  "treatment_timeline": [
    {
      "date": "2024-01-23",
      "report_id": "a5cd6f3cacc7a0a6",
      "report_date": "2024-01-23",
      "doctor": "Janine Silberbauer",
      "nurse": "Lebo Cindi",
      "employee_name": "Lesego Mkhehlane",
      "actions": [
        {
          "category": "Clinical",
          "recommendation": "Normal examination on the day.",
          "status": "Completed",
          "source_field": "ClinicalRecommendations"
        },
        {
          "category": "Men's Health",
          "recommendation": "Please report any new worrying urinary symptoms to your doctor.",
          "status": "Ongoing",
          "source_field": "MensHealthRecommendations"
        },
        {
          "category": "Lifestyle",
          "recommendation": "Start to refine your everyday lifestyle choices for improved future health. These adjustments take a good 3-6 months to show change.",
          "status": "Ongoing",
          "source_field": "OverviewNotes"
        },
        {
          "category": "Women's Health",
          "recommendation": "None",
          "status": "Not specified",
          "source_field": "WomensHealthRecommendation"
        },
        {
          "category": "Supplements",
          "recommendation": "None",
          "status": "Not specified",
          "source_field": "VitaminsOrSupplements"
        }
      ]
    }
  ],
  "generated_at": "2025-08-24 13:28:38",
  "total_reports": 1,
  "total_actions": 5,
  "medical_staff": {
    "doctors": [
      "Janine Silberbauer"
    ],
    "nurses": [
      "Lebo Cindi"
    ]
  }
}