{
  "employee_id": "lkwgt1o4kx9l9ndc",
  "employee_name": "Liza Stead",
  "treatment_timeline": [
    {
      "date": "2022-10-18",
      "report_id": "b93b0e77094684db",
      "report_date": "2022-10-18",
      "doctor": "Christie Pilossof",
      "nurse": "Rebecca Mogale",
      "employee_name": "Liza Stead",
      "actions": [
        {
          "category": "Clinical",
          "recommendation": "Hearing is within normal limits bilaterally, despite from a mild component at 8kHz in the left ear. It is recommended to monitor hearing annually.",
          "status": "Ongoing",
          "source_field": "ClinicalRecommendations"
        },
        {
          "category": "Women's Health",
          "recommendation": "Normal PAP smear and mammogram done this year.",
          "status": "Completed",
          "source_field": "WomensHealthRecommendation"
        },
        {
          "category": "Lifestyle",
          "recommendation": "Age related deterioration of eyesight, migraines which you associate with dehydration and screen time, osteoarthritis in thumbs. Try to drink at least 2 litres of water daily.",
          "status": "Ongoing",
          "source_field": "SymptomScreeningRecommendation"
        },
        {
          "category": "Supplements",
          "recommendation": "Vitamin D , Vitamin C , Zinc , Omega 3 , Jessica Sepel AM and PM formula",
          "status": "Ongoing",
          "source_field": "VitaminsOrSupplements"
        }
      ]
    }
  ],
  "generated_at": "2025-08-24 15:24:10",
  "total_reports": 1,
  "total_actions": 4,
  "medical_staff": {
    "doctors": [
      "Christie Pilossof"
    ],
    "nurses": [
      "Rebecca Mogale"
    ]
  }
}