{
  "employee_id": "ryo095yqdb2g1q7m",
  "employee_name": "Recardo Brown",
  "treatment_timeline": [
    {
      "date": "2022-11-01",
      "report_id": "539975b3f6402331",
      "report_date": "2022-08-31",
      "doctor": "Nokwanda Sithole",
      "nurse": "Lebo Cindi",
      "employee_name": "Recardo Brown",
      "actions": [
        {
          "category": "Clinical",
          "recommendation": "Please report on any new changes in your health in the coming months.",
          "status": "Ongoing",
          "source_field": "Overview Notes"
        },
        {
          "category": "Lifestyle",
          "recommendation": "Once you have recovered, slowly reintroduce exercise into your routine.",
          "status": "Planned",
          "source_field": "Overview Notes"
        },
        {
          "category": "Referral",
          "recommendation": "Please go to your GP with the results so that they can refer you for an abdominal sonar.",
          "status": "Planned",
          "source_field": "Overview Notes"
        },
        {
          "category": "SymptomScreeningRecommendation",
          "recommendation": "Should your lower back pain persist please follow up with your GP in order to get x-rays done and exclude and skeletal pathology.",
          "status": "Planned",
          "source_field": "Overview Notes"
        }
      ]
    }
  ],
  "generated_at": "2025-08-24 16:01:25",
  "total_reports": 1,
  "total_actions": 4,
  "medical_staff": {
    "doctors": [
      "Nokwanda Sithole"
    ],
    "nurses": [
      "Lebo Cindi"
    ]
  }
}