{
  "employee_id": "bc3b68a937564f82",
  "employee_name": "Raylene Oakes",
  "treatment_timeline": [
    {
      "date": "2022-09-22",
      "report_id": "2cecb3bb3d0c49f9",
      "report_date": "Not specified",
      "doctor": "Nokwanda Sithole",
      "nurse": "Lebo Cindi",
      "employee_name": "Raylene Oakes",
      "actions": [
        {
          "category": "Clinical",
          "recommendation": "Optimise homocysteine as suggested and repeat in 6 months",
          "status": "Planned",
          "source_field": "VitalsRecommendation"
        },
        {
          "category": "Clinical",
          "recommendation": "A full audiogram is advised with probable further management by an ENT specialist",
          "status": "Planned",
          "source_field": "SymptomScreeningRecommendation"
        },
        {
          "category": "Lifestyle",
          "recommendation": "Exercise will assist to increase your fitness and decrease your risk of any cardiovascular events",
          "status": "Ongoing",
          "source_field": "Overview Notes"
        },
        {
          "category": "Women's Health",
          "recommendation": "Visit a general practitioner or a gynaecologists for a Pap smear and a Radiologist for a mammogram",
          "status": "Planned",
          "source_field": "WomensHealthRecommendation"
        }
      ]
    }
  ],
  "generated_at": "2025-08-24 14:06:23",
  "total_reports": 1,
  "total_actions": 4,
  "medical_staff": {
    "doctors": [
      "Nokwanda Sithole"
    ],
    "nurses": [
      "Lebo Cindi"
    ]
  }
}