{
  "employee_id": "c009f0053b282c30",
  "employee_name": "Fallon Coetzee",
  "treatment_timeline": [
    {
      "date": "2022-08-11",
      "report_id": "447afc77be629b60",
      "report_date": "2022-08-11",
      "doctor": "Christie Pilossof",
      "nurse": "Rebecca Mogale",
      "employee_name": "Fallon Coetzee",
      "actions": [
        {
          "category": "Women's Health",
          "recommendation": "Follow up with your gynae for planned antenatal visits.",
          "status": "Planned",
          "source_field": "WomensHealthRecommendation"
        },
        {
          "category": "Screening",
          "recommendation": "Please book to see your gynae to confirm your pregnancy and to do an early ultrasound.",
          "status": "Planned",
          "source_field": "Special Investigation Notes"
        },
        {
          "category": "Lifestyle",
          "recommendation": "Please start a prenatal supplement.",
          "status": "Planned",
          "source_field": "VitaminsOrSupplements"
        }
      ]
    }
  ],
  "generated_at": "2025-08-24 14:12:32",
  "total_reports": 1,
  "total_actions": 3,
  "medical_staff": {
    "doctors": [
      "Christie Pilossof"
    ],
    "nurses": [
      "Rebecca Mogale"
    ]
  }
}