{
  "employee_id": "d12558fa7ba2e541",
  "employee_name": "John Pule",
  "treatment_timeline": [
    {
      "date": "2022-07-28",
      "report_id": "0cd7c1782d97190e",
      "report_date": "Not specified",
      "doctor": "Christie Pilossof",
      "nurse": "Rebecca Mogale",
      "employee_name": "John Pule",
      "actions": [
        {
          "category": "Clinical",
          "recommendation": "Normal Clinical examination on the day. Please report any new changes in your health in the coming months.",
          "status": "Ongoing",
          "source_field": "Clinical Recommendations"
        },
        {
          "category": "Men's Health",
          "recommendation": "Over the age of 50 it is recommended that you see a urologist to check your prostate.",
          "status": "Planned",
          "source_field": "Men's Health Recommendations"
        },
        {
          "category": "Women's Health",
          "recommendation": "None",
          "status": "Not specified",
          "source_field": "WomensHealthRecommendation"
        },
        {
          "category": "Lifestyle",
          "recommendation": "To decrease your risk of a cardiovascular event aim for BMI of <25 and waist to height ratio of <50%",
          "status": "Ongoing",
          "source_field": "VitalsRecommendation"
        },
        {
          "category": "Supplements",
          "recommendation": "None",
          "status": "Not specified",
          "source_field": "VitaminsOrSupplements"
        },
        {
          "category": "Screening",
          "recommendation": "None",
          "status": "Not specified",
          "source_field": "SymptomScreeningRecommendation"
        },
        {
          "category": "Monitoring",
          "recommendation": "Your vitamin D level is very low so I do recommend that you supplement with vitamin D.",
          "status": "Ongoing",
          "source_field": "Overview Notes"
        },
        {
          "category": "Referral",
          "recommendation": "You are scheduled for an operation later this month.",
          "status": "Planned",
          "source_field": "Overview Notes"
        },
        {
          "category": "Follow-up",
          "recommendation": "Please report any new changes in your health in the coming months.",
          "status": "Ongoing",
          "source_field": "Clinical Recommendations"
        }
      ]
    }
  ],
  "generated_at": "2025-08-24 14:25:51",
  "total_reports": 1,
  "total_actions": 9,
  "medical_staff": {
    "doctors": [
      "Christie Pilossof"
    ],
    "nurses": [
      "Rebecca Mogale"
    ]
  }
}