{
  "employee_id": "244f18623441d915",
  "employee_name": "Anke Huysamen",
  "treatment_timeline": [
    {
      "date": "2023-07-03",
      "report_id": "0e5af22b9baea800",
      "report_date": "Not specified",
      "doctor": "Janine Silberbauer or Not specified",
      "nurse": "Lebo Cindi or Not specified",
      "employee_name": "Anke Huysamen",
      "actions": [
        {
          "category": "Clinical",
          "recommendation": "Your thyroid functions need to be reviewed and your medication adjusted if needed.",
          "status": "Planned",
          "source_field": "Overview Notes"
        },
        {
          "category": "Lifestyle",
          "recommendation": "Keep refining your everyday lifestyle choices for improved future health. These adjustments take a good 3-6 months to show change.",
          "status": "Ongoing",
          "source_field": "Overview Notes"
        },
        {
          "category": "Lifestyle",
          "recommendation": "Focus on loosing cm around your waist rather than a number on the scale.",
          "status": "Ongoing",
          "source_field": "VitalsRecommendation"
        },
        {
          "category": "Screening",
          "recommendation": "Your fatigue and difficulty in sleep could have a few causes. It is worth reviewing this with your neurologist and Psychiatrist as either your MS or antidepressants could be contributors.",
          "status": "Planned",
          "source_field": "SymptomScreeningRecommendation"
        }
      ]
    }
  ],
  "generated_at": "2025-08-24 12:13:09",
  "total_reports": 1,
  "total_actions": 4,
  "medical_staff": {
    "doctors": [
      "Janine Silberbauer or Not specified"
    ],
    "nurses": [
      "Lebo Cindi or Not specified"
    ]
  }
}