{
  "employee_id": "d2201ed9185508d1",
  "employee_name": "Sugenthree Reddy",
  "treatment_timeline": [
    {
      "date": "2023-08-04",
      "report_id": "fd32ff24bc8b6ec5",
      "report_date": "2023-08-04",
      "doctor": "Fatima Moorad",
      "nurse": "Londeka Mkhwanazi",
      "employee_name": "Sugenthree Reddy",
      "actions": [
        {
          "category": "Clinical",
          "recommendation": "3 monthly BP check ups at GP",
          "status": "Planned",
          "source_field": "VitalsRecommendation"
        },
        {
          "category": "Lifestyle",
          "recommendation": "Intermittent fasting and maintaining a calorie deficit can decrease these levels and the potential risk",
          "status": "Ongoing",
          "source_field": "Overview Notes"
        },
        {
          "category": "Women's Health",
          "recommendation": "Visit a general practitioner or a gynaecologists for a Pap smear and hormonal profile (FSH and LH) and a Radiologist for a mammogram",
          "status": "Planned",
          "source_field": "WomensHealthRecommendation"
        },
        {
          "category": "Supplements",
          "recommendation": "Collagen",
          "status": "Ongoing",
          "source_field": "VitaminsOrSupplements"
        }
      ]
    }
  ],
  "generated_at": "2025-08-24 14:26:31",
  "total_reports": 1,
  "total_actions": 4,
  "medical_staff": {
    "doctors": [
      "Fatima Moorad"
    ],
    "nurses": [
      "Londeka Mkhwanazi"
    ]
  }
}