{
  "employee_id": "md6at9wbi8hdc173",
  "employee_name": "Andrew Smit",
  "treatment_timeline": [
    {
      "date": "2023-04-26",
      "report_id": "65ee8391c5a52d84",
      "report_date": "2023-04-26",
      "doctor": "Cindy Smit",
      "nurse": "Lebo Cindi",
      "employee_name": "Andrew Smit",
      "actions": [
        {
          "category": "Clinical",
          "recommendation": "There are several scars on your neck (cystectomies) and back (sebacious cysts). A mole was noted on the left back that should be regularly reviewed by your Dermatologist.",
          "status": "Ongoing",
          "source_field": "Clinical Recommendations"
        },
        {
          "category": "Clinical",
          "recommendation": "Spasm of the neck muscles caused limited neck movement. Please consider seeing a Physiotherapist.",
          "status": "Planned",
          "source_field": "Clinical Recommendations"
        },
        {
          "category": "Lifestyle",
          "recommendation": "You are experiencing immense stress. Please ensure enough rest, relaxation and mindful self-care. Feel free to reach out for assistance at any time.",
          "status": "Ongoing",
          "source_field": "Overview Notes"
        },
        {
          "category": "Supplements",
          "recommendation": "Multivitamin",
          "status": "Not specified",
          "source_field": "VitaminsOrSupplements"
        }
      ]
    }
  ],
  "generated_at": "2025-08-24 15:30:31",
  "total_reports": 1,
  "total_actions": 4,
  "medical_staff": {
    "doctors": [
      "Cindy Smit"
    ],
    "nurses": [
      "Lebo Cindi"
    ]
  }
}